pycurrencyid/README.md
pycurrencyid/__init__.py
pycurrencyid/mata_uang/__init__.py
pycurrencyid/mata_uang/afrika/__init__.py
pycurrencyid/mata_uang/afrika/afrika.json
pycurrencyid/mata_uang/afrika/afrika.py
pycurrencyid/mata_uang/amerika/__init__.py
pycurrencyid/mata_uang/amerika/amerika_selatan.json
pycurrencyid/mata_uang/amerika/amerika_selatan.py
pycurrencyid/mata_uang/amerika/amerika_utara.json
pycurrencyid/mata_uang/amerika/amerika_utara.py
pycurrencyid/mata_uang/asia/__init__.py
pycurrencyid/mata_uang/asia/asia.json
pycurrencyid/mata_uang/asia/asia.py
pycurrencyid/mata_uang/australia/__init__.py
pycurrencyid/mata_uang/australia/australia.json
pycurrencyid/mata_uang/australia/australia.py
pycurrencyid/mata_uang/eropa/__init__.py
pycurrencyid/mata_uang/eropa/eropa.json
pycurrencyid/mata_uang/eropa/eropa.py
pycurrencyid/mata_uang/mata_uang.py
pycurrencyid-1.4.3.dist-info/METADATA
pycurrencyid-1.4.3.dist-info/WHEEL
pycurrencyid-1.4.3.dist-info/RECORD
