Metadata-Version: 2.1
Name: pycurrencyid
Version: 1.4.3
Summary: This library contains data on country names, currencies and abbreviations which are stored and packaged in the form of a JSON file
License: MIT
Keywords: mata uang,currency,indonesia,data,pycurrency,indo,wilayah,daerah,administrasi
Author: harigro
Author-email: trierbank@gmail.com
Requires-Python: >=3.10,<4.0
Classifier: License :: OSI Approved :: MIT License
Classifier: Programming Language :: Python
Classifier: Programming Language :: Python :: 3
Classifier: Programming Language :: Python :: 3.10
Classifier: Programming Language :: Python :: 3.11
Classifier: Programming Language :: Python :: 3 :: Only
Project-URL: Documentation, https://github.com/harigro/pycurrencyid
Project-URL: Homepage, https://github.com/harigro/pycurrencyid
Project-URL: Repository, https://github.com/harigro/pycurrencyid
